repository_sqlalchemy/__init__.py
repository_sqlalchemy/base_repository.py
repository_sqlalchemy/database_config.py
repository_sqlalchemy/metaclasses.py
repository_sqlalchemy/session_management.py
repository_sqlalchemy/transaction_management.py
tests/__init__.py
tests/conftest.py
tests/test_model.py
tests/test_repository.py
tests/test_transactional_inheritance.py
repository_sqlalchemy-0.1.8.dist-info/METADATA
repository_sqlalchemy-0.1.8.dist-info/WHEEL
repository_sqlalchemy-0.1.8.dist-info/top_level.txt
repository_sqlalchemy-0.1.8.dist-info/RECORD
