Metadata-Version: 2.4
Name: repository_sqlalchemy
Version: 0.1.8
Summary: A small library to simplify SQLAlchemy usage with FastAPI
Author-email: Ryan Zheng <ryan.zheng.work@gmail.com>
License: MIT
Project-URL: Homepage, https://github.com/ryan-zheng-teki/repository_sqlalchemy
Project-URL: Repository, https://github.com/ryan-zheng-teki/repository_sqlalchemy
Project-URL: Issues, https://github.com/ryan-zheng-teki/repository_sqlalchemy/issues
Classifier: Development Status :: 3 - Alpha
Classifier: Intended Audience :: Developers
Classifier: License :: OSI Approved :: MIT License
Classifier: Programming Language :: Python :: 3.10
Requires-Python: >=3.8
Requires-Dist: sqlalchemy>=2.0.31
Provides-Extra: dev
Requires-Dist: pytest>=8.2.2; extra == "dev"
Requires-Dist: pytest-asyncio>=0.23.7; extra == "dev"
